solsim/__init__.py
solsim/constant.py
solsim/simulation.py
solsim/system.py
solsim/type.py
solsim/visualize.py
solsim-0.1.7.dist-info/LICENSE
solsim-0.1.7.dist-info/WHEEL
solsim-0.1.7.dist-info/METADATA
solsim-0.1.7.dist-info/RECORD
