Metadata-Version: 2.1
Name: solsim
Version: 0.1.7
Summary: The Solana complex systems simulator.
Home-page: https://github.com/cavaunpeu/solsim
License: MIT
Author: Will Wolf
Author-email: williamabrwolf@gmail.com
Requires-Python: >=3.10,<4.0
Classifier: License :: OSI Approved :: MIT License
Classifier: Programming Language :: Python :: 3
Classifier: Programming Language :: Python :: 3.10
Requires-Dist: anchorpy (>=0.6.4,<0.7.0)
Requires-Dist: feather-format (>=0.4.1,<0.5.0)
Requires-Dist: numpy (>=1.22.1,<2.0.0)
Requires-Dist: pandas (>=1.4.0,<2.0.0)
Requires-Dist: streamlit (>=1.5.0,<2.0.0)
Requires-Dist: tqdm (>=4.62.3,<5.0.0)
Project-URL: Repository, https://github.com/cavaunpeu/solsim
